{
  "blood_donors": {
    "status": "OK",
    "count": 0,
    "sample": []
  },
  "organ_donors": {
    "status": "OK",
    "count": 0,
    "sample": []
  },
  "hospitals": {
    "status": "OK",
    "count": 0,
    "sample": []
  },
  "requests": {
    "status": "OK",
    "count": 0,
    "sample": []
  },
  "matches": {
    "status": "ERROR",
    "message": "Could not find the table 'public.matches' in the schema cache"
  },
  "match_results": {
    "status": "OK",
    "count": 0,
    "sample": []
  },
  "recipients": {
    "status": "OK",
    "count": 800,
    "sample": [
      {
        "id": "930d4a3c-cff7-4a9f-a588-4f0469e29748",
        "recipient_id": "R001",
        "first_name": "Fatima",
        "last_name": "Khan",
        "age": 45,
        "gender": "Female",
        "blood_type": "A+",
        "required_organ": "Kidney",
        "time_got": "2024-01-20T14:30:00",
        "medical_conditions": "Diabetes",
        "cancer_stage": "None",
        "hepatitis_status": "Negative",
        "contact_number": "0312-3456789",
        "city": "Karachi",
        "hospital_name": "Jinnah Postgraduate Medical Centre",
        "created_at": "2026-04-06T09:45:29.018582",
        "latitude": null,
        "longitude": null,
        "user_id": null
      },
      {
        "id": "8fe0a098-b0d1-48f7-904e-514d66a57e7c",
        "recipient_id": "R002",
        "first_name": "Ahmed",
        "last_name": "Malik",
        "age": 52,
        "gender": "Male",
        "blood_type": "B-",
        "required_organ": "Liver",
        "time_got": "2024-02-05T09:15:00",
        "medical_conditions": "Hypertension",
        "cancer_stage": "None",
        "hepatitis_status": "Negative",
        "contact_number": "0333-4567890",
        "city": "Lahore",
        "hospital_name": "Mayo Hospital",
        "created_at": "2026-04-06T09:45:29.018582",
        "latitude": null,
        "longitude": null,
        "user_id": null
      },
      {
        "id": "e22d9222-895a-4533-a529-f8a1a04b2440",
        "recipient_id": "R003",
        "first_name": "Sara",
        "last_name": "Ahmed",
        "age": 28,
        "gender": "Female",
        "blood_type": "O+",
        "required_organ": "Heart",
        "time_got": "2024-01-15T11:45:00",
        "medical_conditions": "Asthma",
        "cancer_stage": "None",
        "hepatitis_status": "Negative",
        "contact_number": "0301-5678901",
        "city": "Islamabad",
        "hospital_name": "Pakistan Institute of Medical Sciences",
        "created_at": "2026-04-06T09:45:29.018582",
        "latitude": null,
        "longitude": null,
        "user_id": null
      }
    ]
  }
}